LICENSE
README.md
setup.cfg
setup.py
importAirfoil/__init__.py
importAirfoil/importAirfoil.py
importAirfoil.egg-info/PKG-INFO
importAirfoil.egg-info/SOURCES.txt
importAirfoil.egg-info/dependency_links.txt
importAirfoil.egg-info/top_level.txt