Metadata-Version: 2.1
Name: importAirfoil
Version: 1.3.0
Summary: Airfoil coordinates import function
Home-page: https://github.com/VAZMFB/Python-importAirfoil
Author: Miloš Petrašinović
Author-email: mpetrasinovic@mas.bg.ac.rs
License: GPL-3.0-or-later
Download-URL: https://github.com/VAZMFB/Python-importAirfoil/archive/refs/tags/1.3.0.tar.gz
Keywords: airfoil,import-airfoil
Platform: UNKNOWN
License-File: LICENSE
